<?xml version="1.0" encoding="UTF-8"?>
<config xmlns="http://www.knime.org/2008/09/XMLConfig" xmlns:xsi="http://www.w3.org/2001/XMLSchema-instance" xsi:schemaLocation="http://www.knime.org/2008/09/XMLConfig http://www.knime.org/XMLConfig_2008_09.xsd" key="spec.xml">
    <entry key="spec_name" type="xstring" value="default"/>
    <entry key="number_columns" type="xint" value="23"/>
    <config key="column_spec_0">
        <entry key="column_name" type="xstring" value="Name"/>
        <config key="element_names">
            <entry key="array-size" type="xint" value="0"/>
        </config>
        <config key="column_type">
            <entry key="cell_class" type="xstring" value="org.knime.core.data.def.StringCell"/>
        </config>
        <config key="column_domain">
            <config key="possible_values">
                <entry key="array-size" type="xint" value="10"/>
                <config key="0">
                    <entry key="datacell" type="xstring" value="org.knime.core.data.def.StringCell"/>
                    <config key="org.knime.core.data.def.StringCell">
                        <entry key="StringCell" type="xstring" value="Unnamed: 0"/>
                    </config>
                </config>
                <config key="1">
                    <entry key="datacell" type="xstring" value="org.knime.core.data.def.StringCell"/>
                    <config key="org.knime.core.data.def.StringCell">
                        <entry key="StringCell" type="xstring" value="price"/>
                    </config>
                </config>
                <config key="2">
                    <entry key="datacell" type="xstring" value="org.knime.core.data.def.StringCell"/>
                    <config key="org.knime.core.data.def.StringCell">
                        <entry key="StringCell" type="xstring" value="rooms"/>
                    </config>
                </config>
                <config key="3">
                    <entry key="datacell" type="xstring" value="org.knime.core.data.def.StringCell"/>
                    <config key="org.knime.core.data.def.StringCell">
                        <entry key="StringCell" type="xstring" value="bathroom"/>
                    </config>
                </config>
                <config key="4">
                    <entry key="datacell" type="xstring" value="org.knime.core.data.def.StringCell"/>
                    <config key="org.knime.core.data.def.StringCell">
                        <entry key="StringCell" type="xstring" value="lift"/>
                    </config>
                </config>
                <config key="5">
                    <entry key="datacell" type="xstring" value="org.knime.core.data.def.StringCell"/>
                    <config key="org.knime.core.data.def.StringCell">
                        <entry key="StringCell" type="xstring" value="terrace"/>
                    </config>
                </config>
                <config key="6">
                    <entry key="datacell" type="xstring" value="org.knime.core.data.def.StringCell"/>
                    <config key="org.knime.core.data.def.StringCell">
                        <entry key="StringCell" type="xstring" value="square_meters"/>
                    </config>
                </config>
                <config key="7">
                    <entry key="datacell" type="xstring" value="org.knime.core.data.def.StringCell"/>
                    <config key="org.knime.core.data.def.StringCell">
                        <entry key="StringCell" type="xstring" value="real_state"/>
                    </config>
                </config>
                <config key="8">
                    <entry key="datacell" type="xstring" value="org.knime.core.data.def.StringCell"/>
                    <config key="org.knime.core.data.def.StringCell">
                        <entry key="StringCell" type="xstring" value="neighborhood"/>
                    </config>
                </config>
                <config key="9">
                    <entry key="datacell" type="xstring" value="org.knime.core.data.def.StringCell"/>
                    <config key="org.knime.core.data.def.StringCell">
                        <entry key="StringCell" type="xstring" value="square_meters_price"/>
                    </config>
                </config>
            </config>
        </config>
        <config key="column_properties"/>
        <config key="meta_data"/>
    </config>
    <config key="column_spec_1">
        <entry key="column_name" type="xstring" value="Type"/>
        <config key="element_names">
            <entry key="array-size" type="xint" value="0"/>
        </config>
        <config key="column_type">
            <entry key="cell_class" type="xstring" value="org.knime.core.data.def.StringCell"/>
        </config>
        <config key="column_domain">
            <config key="possible_values">
                <entry key="array-size" type="xint" value="3"/>
                <config key="0">
                    <entry key="datacell" type="xstring" value="org.knime.core.data.def.StringCell"/>
                    <config key="org.knime.core.data.def.StringCell">
                        <entry key="StringCell" type="xstring" value="Number (integer)"/>
                    </config>
                </config>
                <config key="1">
                    <entry key="datacell" type="xstring" value="org.knime.core.data.def.StringCell"/>
                    <config key="org.knime.core.data.def.StringCell">
                        <entry key="StringCell" type="xstring" value="Number (double)"/>
                    </config>
                </config>
                <config key="2">
                    <entry key="datacell" type="xstring" value="org.knime.core.data.def.StringCell"/>
                    <config key="org.knime.core.data.def.StringCell">
                        <entry key="StringCell" type="xstring" value="String"/>
                    </config>
                </config>
            </config>
        </config>
        <config key="column_properties"/>
        <config key="meta_data"/>
    </config>
    <config key="column_spec_2">
        <entry key="column_name" type="xstring" value="# Missing values"/>
        <config key="element_names">
            <entry key="array-size" type="xint" value="0"/>
        </config>
        <config key="column_type">
            <entry key="cell_class" type="xstring" value="org.knime.core.data.def.LongCell"/>
        </config>
        <config key="column_domain">
            <config key="lower_bound">
                <entry key="datacell" type="xstring" value="org.knime.core.data.def.LongCell"/>
                <config key="org.knime.core.data.def.LongCell">
                    <entry key="LongCell" type="xlong" value="0"/>
                </config>
            </config>
            <config key="upper_bound">
                <entry key="datacell" type="xstring" value="org.knime.core.data.def.LongCell"/>
                <config key="org.knime.core.data.def.LongCell">
                    <entry key="LongCell" type="xlong" value="918"/>
                </config>
            </config>
        </config>
        <config key="column_properties"/>
        <config key="meta_data"/>
    </config>
    <config key="column_spec_3">
        <entry key="column_name" type="xstring" value="# Unique values"/>
        <config key="element_names">
            <entry key="array-size" type="xint" value="0"/>
        </config>
        <config key="column_type">
            <entry key="cell_class" type="xstring" value="org.knime.core.data.def.LongCell"/>
        </config>
        <config key="column_domain">
            <config key="lower_bound">
                <entry key="datacell" type="xstring" value="org.knime.core.data.def.LongCell"/>
                <config key="org.knime.core.data.def.LongCell">
                    <entry key="LongCell" type="xlong" value="2"/>
                </config>
            </config>
            <config key="upper_bound">
                <entry key="datacell" type="xstring" value="org.knime.core.data.def.LongCell"/>
                <config key="org.knime.core.data.def.LongCell">
                    <entry key="LongCell" type="xlong" value="16376"/>
                </config>
            </config>
        </config>
        <config key="column_properties"/>
        <config key="meta_data"/>
    </config>
    <config key="column_spec_4">
        <entry key="column_name" type="xstring" value="Minimum"/>
        <config key="element_names">
            <entry key="array-size" type="xint" value="0"/>
        </config>
        <config key="column_type">
            <entry key="cell_class" type="xstring" value="org.knime.core.data.def.DoubleCell"/>
        </config>
        <config key="column_domain">
            <config key="lower_bound">
                <entry key="datacell" type="xstring" value="org.knime.core.data.def.DoubleCell"/>
                <config key="org.knime.core.data.def.DoubleCell">
                    <entry key="DoubleCell" type="xdouble" value="0.0"/>
                </config>
            </config>
            <config key="upper_bound">
                <entry key="datacell" type="xstring" value="org.knime.core.data.def.DoubleCell"/>
                <config key="org.knime.core.data.def.DoubleCell">
                    <entry key="DoubleCell" type="xdouble" value="320.0"/>
                </config>
            </config>
        </config>
        <config key="column_properties"/>
        <config key="meta_data"/>
    </config>
    <config key="column_spec_5">
        <entry key="column_name" type="xstring" value="Maximum"/>
        <config key="element_names">
            <entry key="array-size" type="xint" value="0"/>
        </config>
        <config key="column_type">
            <entry key="cell_class" type="xstring" value="org.knime.core.data.def.DoubleCell"/>
        </config>
        <config key="column_domain">
            <config key="lower_bound">
                <entry key="datacell" type="xstring" value="org.knime.core.data.def.DoubleCell"/>
                <config key="org.knime.core.data.def.DoubleCell">
                    <entry key="DoubleCell" type="xdouble" value="8.0"/>
                </config>
            </config>
            <config key="upper_bound">
                <entry key="datacell" type="xstring" value="org.knime.core.data.def.DoubleCell"/>
                <config key="org.knime.core.data.def.DoubleCell">
                    <entry key="DoubleCell" type="xdouble" value="16375.0"/>
                </config>
            </config>
        </config>
        <config key="column_properties"/>
        <config key="meta_data"/>
    </config>
    <config key="column_spec_6">
        <entry key="column_name" type="xstring" value="1% Quantile"/>
        <config key="element_names">
            <entry key="array-size" type="xint" value="0"/>
        </config>
        <config key="column_type">
            <entry key="cell_class" type="xstring" value="org.knime.core.data.def.DoubleCell"/>
        </config>
        <config key="column_domain">
            <config key="lower_bound">
                <entry key="datacell" type="xstring" value="org.knime.core.data.def.DoubleCell"/>
                <config key="org.knime.core.data.def.DoubleCell">
                    <entry key="DoubleCell" type="xdouble" value="0.0"/>
                </config>
            </config>
            <config key="upper_bound">
                <entry key="datacell" type="xstring" value="org.knime.core.data.def.DoubleCell"/>
                <config key="org.knime.core.data.def.DoubleCell">
                    <entry key="DoubleCell" type="xdouble" value="590.0"/>
                </config>
            </config>
        </config>
        <config key="column_properties"/>
        <config key="meta_data"/>
    </config>
    <config key="column_spec_7">
        <entry key="column_name" type="xstring" value="5% Quantile"/>
        <config key="element_names">
            <entry key="array-size" type="xint" value="0"/>
        </config>
        <config key="column_type">
            <entry key="cell_class" type="xstring" value="org.knime.core.data.def.DoubleCell"/>
        </config>
        <config key="column_domain">
            <config key="lower_bound">
                <entry key="datacell" type="xstring" value="org.knime.core.data.def.DoubleCell"/>
                <config key="org.knime.core.data.def.DoubleCell">
                    <entry key="DoubleCell" type="xdouble" value="0.936"/>
                </config>
            </config>
            <config key="upper_bound">
                <entry key="datacell" type="xstring" value="org.knime.core.data.def.DoubleCell"/>
                <config key="org.knime.core.data.def.DoubleCell">
                    <entry key="DoubleCell" type="xdouble" value="817.85"/>
                </config>
            </config>
        </config>
        <config key="column_properties"/>
        <config key="meta_data"/>
    </config>
    <config key="column_spec_8">
        <entry key="column_name" type="xstring" value="10% Quantile"/>
        <config key="element_names">
            <entry key="array-size" type="xint" value="0"/>
        </config>
        <config key="column_type">
            <entry key="cell_class" type="xstring" value="org.knime.core.data.def.DoubleCell"/>
        </config>
        <config key="column_domain">
            <config key="lower_bound">
                <entry key="datacell" type="xstring" value="org.knime.core.data.def.DoubleCell"/>
                <config key="org.knime.core.data.def.DoubleCell">
                    <entry key="DoubleCell" type="xdouble" value="0.97"/>
                </config>
            </config>
            <config key="upper_bound">
                <entry key="datacell" type="xstring" value="org.knime.core.data.def.DoubleCell"/>
                <config key="org.knime.core.data.def.DoubleCell">
                    <entry key="DoubleCell" type="xdouble" value="1636.7"/>
                </config>
            </config>
        </config>
        <config key="column_properties"/>
        <config key="meta_data"/>
    </config>
    <config key="column_spec_9">
        <entry key="column_name" type="xstring" value="25% Quantile"/>
        <config key="element_names">
            <entry key="array-size" type="xint" value="0"/>
        </config>
        <config key="column_type">
            <entry key="cell_class" type="xstring" value="org.knime.core.data.def.DoubleCell"/>
        </config>
        <config key="column_domain">
            <config key="lower_bound">
                <entry key="datacell" type="xstring" value="org.knime.core.data.def.DoubleCell"/>
                <config key="org.knime.core.data.def.DoubleCell">
                    <entry key="DoubleCell" type="xdouble" value="1.0"/>
                </config>
            </config>
            <config key="upper_bound">
                <entry key="datacell" type="xstring" value="org.knime.core.data.def.DoubleCell"/>
                <config key="org.knime.core.data.def.DoubleCell">
                    <entry key="DoubleCell" type="xdouble" value="4093.25"/>
                </config>
            </config>
        </config>
        <config key="column_properties"/>
        <config key="meta_data"/>
    </config>
    <config key="column_spec_10">
        <entry key="column_name" type="xstring" value="50% Quantile (Median)"/>
        <config key="element_names">
            <entry key="array-size" type="xint" value="0"/>
        </config>
        <config key="column_type">
            <entry key="cell_class" type="xstring" value="org.knime.core.data.def.DoubleCell"/>
        </config>
        <config key="column_domain">
            <config key="lower_bound">
                <entry key="datacell" type="xstring" value="org.knime.core.data.def.DoubleCell"/>
                <config key="org.knime.core.data.def.DoubleCell">
                    <entry key="DoubleCell" type="xdouble" value="1.037"/>
                </config>
            </config>
            <config key="upper_bound">
                <entry key="datacell" type="xstring" value="org.knime.core.data.def.DoubleCell"/>
                <config key="org.knime.core.data.def.DoubleCell">
                    <entry key="DoubleCell" type="xdouble" value="8187.5"/>
                </config>
            </config>
        </config>
        <config key="column_properties"/>
        <config key="meta_data"/>
    </config>
    <config key="column_spec_11">
        <entry key="column_name" type="xstring" value="75% Quantile"/>
        <config key="element_names">
            <entry key="array-size" type="xint" value="0"/>
        </config>
        <config key="column_type">
            <entry key="cell_class" type="xstring" value="org.knime.core.data.def.DoubleCell"/>
        </config>
        <config key="column_domain">
            <config key="lower_bound">
                <entry key="datacell" type="xstring" value="org.knime.core.data.def.DoubleCell"/>
                <config key="org.knime.core.data.def.DoubleCell">
                    <entry key="DoubleCell" type="xdouble" value="2.0"/>
                </config>
            </config>
            <config key="upper_bound">
                <entry key="datacell" type="xstring" value="org.knime.core.data.def.DoubleCell"/>
                <config key="org.knime.core.data.def.DoubleCell">
                    <entry key="DoubleCell" type="xdouble" value="12281.75"/>
                </config>
            </config>
        </config>
        <config key="column_properties"/>
        <config key="meta_data"/>
    </config>
    <config key="column_spec_12">
        <entry key="column_name" type="xstring" value="90% Quantile"/>
        <config key="element_names">
            <entry key="array-size" type="xint" value="0"/>
        </config>
        <config key="column_type">
            <entry key="cell_class" type="xstring" value="org.knime.core.data.def.DoubleCell"/>
        </config>
        <config key="column_domain">
            <config key="lower_bound">
                <entry key="datacell" type="xstring" value="org.knime.core.data.def.DoubleCell"/>
                <config key="org.knime.core.data.def.DoubleCell">
                    <entry key="DoubleCell" type="xdouble" value="2.127"/>
                </config>
            </config>
            <config key="upper_bound">
                <entry key="datacell" type="xstring" value="org.knime.core.data.def.DoubleCell"/>
                <config key="org.knime.core.data.def.DoubleCell">
                    <entry key="DoubleCell" type="xdouble" value="14738.300000000001"/>
                </config>
            </config>
        </config>
        <config key="column_properties"/>
        <config key="meta_data"/>
    </config>
    <config key="column_spec_13">
        <entry key="column_name" type="xstring" value="95% Quantile"/>
        <config key="element_names">
            <entry key="array-size" type="xint" value="0"/>
        </config>
        <config key="column_type">
            <entry key="cell_class" type="xstring" value="org.knime.core.data.def.DoubleCell"/>
        </config>
        <config key="column_domain">
            <config key="lower_bound">
                <entry key="datacell" type="xstring" value="org.knime.core.data.def.DoubleCell"/>
                <config key="org.knime.core.data.def.DoubleCell">
                    <entry key="DoubleCell" type="xdouble" value="3.0"/>
                </config>
            </config>
            <config key="upper_bound">
                <entry key="datacell" type="xstring" value="org.knime.core.data.def.DoubleCell"/>
                <config key="org.knime.core.data.def.DoubleCell">
                    <entry key="DoubleCell" type="xdouble" value="15557.15"/>
                </config>
            </config>
        </config>
        <config key="column_properties"/>
        <config key="meta_data"/>
    </config>
    <config key="column_spec_14">
        <entry key="column_name" type="xstring" value="99% Quantile"/>
        <config key="element_names">
            <entry key="array-size" type="xint" value="0"/>
        </config>
        <config key="column_type">
            <entry key="cell_class" type="xstring" value="org.knime.core.data.def.DoubleCell"/>
        </config>
        <config key="column_domain">
            <config key="lower_bound">
                <entry key="datacell" type="xstring" value="org.knime.core.data.def.DoubleCell"/>
                <config key="org.knime.core.data.def.DoubleCell">
                    <entry key="DoubleCell" type="xdouble" value="4.0"/>
                </config>
            </config>
            <config key="upper_bound">
                <entry key="datacell" type="xstring" value="org.knime.core.data.def.DoubleCell"/>
                <config key="org.knime.core.data.def.DoubleCell">
                    <entry key="DoubleCell" type="xdouble" value="16212.23"/>
                </config>
            </config>
        </config>
        <config key="column_properties"/>
        <config key="meta_data"/>
    </config>
    <config key="column_spec_15">
        <entry key="column_name" type="xstring" value="Mean"/>
        <config key="element_names">
            <entry key="array-size" type="xint" value="0"/>
        </config>
        <config key="column_type">
            <entry key="cell_class" type="xstring" value="org.knime.core.data.def.DoubleCell"/>
        </config>
        <config key="column_domain">
            <config key="lower_bound">
                <entry key="datacell" type="xstring" value="org.knime.core.data.def.DoubleCell"/>
                <config key="org.knime.core.data.def.DoubleCell">
                    <entry key="DoubleCell" type="xdouble" value="1.5046824066545705"/>
                </config>
            </config>
            <config key="upper_bound">
                <entry key="datacell" type="xstring" value="org.knime.core.data.def.DoubleCell"/>
                <config key="org.knime.core.data.def.DoubleCell">
                    <entry key="DoubleCell" type="xdouble" value="8187.5"/>
                </config>
            </config>
        </config>
        <config key="column_properties"/>
        <config key="meta_data"/>
    </config>
    <config key="column_spec_16">
        <entry key="column_name" type="xstring" value="Mean Absolute Deviation"/>
        <config key="element_names">
            <entry key="array-size" type="xint" value="0"/>
        </config>
        <config key="column_type">
            <entry key="cell_class" type="xstring" value="org.knime.core.data.def.DoubleCell"/>
        </config>
        <config key="column_domain">
            <config key="lower_bound">
                <entry key="datacell" type="xstring" value="org.knime.core.data.def.DoubleCell"/>
                <config key="org.knime.core.data.def.DoubleCell">
                    <entry key="DoubleCell" type="xdouble" value="0.5979461545660303"/>
                </config>
            </config>
            <config key="upper_bound">
                <entry key="datacell" type="xstring" value="org.knime.core.data.def.DoubleCell"/>
                <config key="org.knime.core.data.def.DoubleCell">
                    <entry key="DoubleCell" type="xdouble" value="4094.0"/>
                </config>
            </config>
        </config>
        <config key="column_properties"/>
        <config key="meta_data"/>
    </config>
    <config key="column_spec_17">
        <entry key="column_name" type="xstring" value="Standard Deviation"/>
        <config key="element_names">
            <entry key="array-size" type="xint" value="0"/>
        </config>
        <config key="column_type">
            <entry key="cell_class" type="xstring" value="org.knime.core.data.def.DoubleCell"/>
        </config>
        <config key="column_domain">
            <config key="lower_bound">
                <entry key="datacell" type="xstring" value="org.knime.core.data.def.DoubleCell"/>
                <config key="org.knime.core.data.def.DoubleCell">
                    <entry key="DoubleCell" type="xdouble" value="0.723192481537818"/>
                </config>
            </config>
            <config key="upper_bound">
                <entry key="datacell" type="xstring" value="org.knime.core.data.def.DoubleCell"/>
                <config key="org.knime.core.data.def.DoubleCell">
                    <entry key="DoubleCell" type="xdouble" value="4727.488339488528"/>
                </config>
            </config>
        </config>
        <config key="column_properties"/>
        <config key="meta_data"/>
    </config>
    <config key="column_spec_18">
        <entry key="column_name" type="xstring" value="Sum"/>
        <config key="element_names">
            <entry key="array-size" type="xint" value="0"/>
        </config>
        <config key="column_type">
            <entry key="cell_class" type="xstring" value="org.knime.core.data.def.DoubleCell"/>
        </config>
        <config key="column_domain">
            <config key="lower_bound">
                <entry key="datacell" type="xstring" value="org.knime.core.data.def.DoubleCell"/>
                <config key="org.knime.core.data.def.DoubleCell">
                    <entry key="DoubleCell" type="xdouble" value="24058.36699999993"/>
                </config>
            </config>
            <config key="upper_bound">
                <entry key="datacell" type="xstring" value="org.knime.core.data.def.DoubleCell"/>
                <config key="org.knime.core.data.def.DoubleCell">
                    <entry key="DoubleCell" type="xdouble" value="1.340785E8"/>
                </config>
            </config>
        </config>
        <config key="column_properties"/>
        <config key="meta_data"/>
    </config>
    <config key="column_spec_19">
        <entry key="column_name" type="xstring" value="Variance"/>
        <config key="element_names">
            <entry key="array-size" type="xint" value="0"/>
        </config>
        <config key="column_type">
            <entry key="cell_class" type="xstring" value="org.knime.core.data.def.DoubleCell"/>
        </config>
        <config key="column_domain">
            <config key="lower_bound">
                <entry key="datacell" type="xstring" value="org.knime.core.data.def.DoubleCell"/>
                <config key="org.knime.core.data.def.DoubleCell">
                    <entry key="DoubleCell" type="xdouble" value="0.5230073653528272"/>
                </config>
            </config>
            <config key="upper_bound">
                <entry key="datacell" type="xstring" value="org.knime.core.data.def.DoubleCell"/>
                <config key="org.knime.core.data.def.DoubleCell">
                    <entry key="DoubleCell" type="xdouble" value="2.2349146E7"/>
                </config>
            </config>
        </config>
        <config key="column_properties"/>
        <config key="meta_data"/>
    </config>
    <config key="column_spec_20">
        <entry key="column_name" type="xstring" value="10 most common values"/>
        <config key="element_names">
            <entry key="array-size" type="xint" value="0"/>
        </config>
        <config key="column_type">
            <entry key="cell_class" type="xstring" value="org.knime.core.data.def.StringCell"/>
        </config>
        <config key="column_domain">
            <config key="possible_values">
                <entry key="array-size" type="xint" value="10"/>
                <config key="0">
                    <entry key="datacell" type="xstring" value="org.knime.core.data.def.StringCell"/>
                    <config key="org.knime.core.data.def.StringCell">
                        <entry key="StringCell" type="xstring" value="0 (1; 0.01%), 1 (1; 0.01%), 2 (1; 0.01%), 3 (1; 0.01%), 4 (1; 0.01%), 5 (1; 0.01%), 6 (1; 0.01%), 7 (1; 0.01%), 8 (1; 0.01%), 9 (1; 0.01%)"/>
                    </config>
                </config>
                <config key="1">
                    <entry key="datacell" type="xstring" value="org.knime.core.data.def.StringCell"/>
                    <config key="org.knime.core.data.def.StringCell">
                        <entry key="StringCell" type="xstring" value="1,100 (716; 4.37%), 950 (690; 4.21%), 850 (641; 3.91%), 900 (632; 3.86%), 1,200 (537; 3.28%), 800 (527; 3.22%), 1,000 (471; 2.88%), 750 (450; 2.75%), 1,150 (421; 2.57%), 1,300 (375; 2.29%)"/>
                    </config>
                </config>
                <config key="2">
                    <entry key="datacell" type="xstring" value="org.knime.core.data.def.StringCell"/>
                    <config key="org.knime.core.data.def.StringCell">
                        <entry key="StringCell" type="xstring" value="2 (2608; 16.33%), 3 (2461; 15.41%), 1 (1600; 10.02%), 4 (1061; 6.65%), 0 (399; 2.5%), 5 (232; 1.45%), 6 (28; 0.18%), 0.91 (19; 0.12%), 0.981 (15; 0.09%), 0.917 (14; 0.09%)"/>
                    </config>
                </config>
                <config key="3">
                    <entry key="datacell" type="xstring" value="org.knime.core.data.def.StringCell"/>
                    <config key="org.knime.core.data.def.StringCell">
                        <entry key="StringCell" type="xstring" value="1 (4873; 30.48%), 2 (2742; 17.15%), 3 (421; 2.63%), 4 (121; 0.76%), 5 (41; 0.26%), 1.094 (36; 0.23%), 0.986 (35; 0.22%), 1.051 (35; 0.22%), 0.939 (34; 0.21%), 1.06 (34; 0.21%)"/>
                    </config>
                </config>
                <config key="4">
                    <entry key="datacell" type="xstring" value="org.knime.core.data.def.StringCell"/>
                    <config key="org.knime.core.data.def.StringCell">
                        <entry key="StringCell" type="xstring" value="True (11246; 68.67%), False (5130; 31.33%)"/>
                    </config>
                </config>
                <config key="5">
                    <entry key="datacell" type="xstring" value="org.knime.core.data.def.StringCell"/>
                    <config key="org.knime.core.data.def.StringCell">
                        <entry key="StringCell" type="xstring" value="False (12770; 77.98%), True (3606; 22.02%)"/>
                    </config>
                </config>
                <config key="6">
                    <entry key="datacell" type="xstring" value="org.knime.core.data.def.StringCell"/>
                    <config key="org.knime.core.data.def.StringCell">
                        <entry key="StringCell" type="xstring" value="70 (431; 2.7%), 60 (395; 2.47%), 80 (386; 2.42%), 50 (336; 2.1%), 65 (335; 2.1%), 55 (295; 1.85%), 75 (294; 1.84%), 90 (244; 1.53%), 85 (219; 1.37%), 45 (216; 1.35%)"/>
                    </config>
                </config>
                <config key="7">
                    <entry key="datacell" type="xstring" value="org.knime.core.data.def.StringCell"/>
                    <config key="org.knime.core.data.def.StringCell">
                        <entry key="StringCell" type="xstring" value="flat (12650; 81.83%), apartment (1967; 12.72%), attic (633; 4.09%), study (208; 1.35%)"/>
                    </config>
                </config>
                <config key="8">
                    <entry key="datacell" type="xstring" value="org.knime.core.data.def.StringCell"/>
                    <config key="org.knime.core.data.def.StringCell">
                        <entry key="StringCell" type="xstring" value="Eixample (4795; 29.28%), Sarria-Sant Gervasi (2765; 16.88%), Ciutat Vella (2716; 16.59%), Gràcia (1416; 8.65%), Sant Martí (1257; 7.68%), Sants-Montjuïc (1165; 7.11%), Les Corts (1045; 6.38%), Horta- Guinardo (638; 3.9%), Sant Andreu (368; 2.25%), Nou Barris (211; 1.29%)"/>
                    </config>
                </config>
                <config key="9">
                    <entry key="datacell" type="xstring" value="org.knime.core.data.def.StringCell"/>
                    <config key="org.knime.core.data.def.StringCell">
                        <entry key="StringCell" type="xstring" value="20 (125; 0.78%), 15 (121; 0.76%), 12.5 (111; 0.7%), 16.667 (86; 0.54%), 10 (69; 0.43%), 13.333 (64; 0.4%), 14.286 (61; 0.38%), 14 (59; 0.37%), 17.5 (58; 0.36%), 16 (56; 0.35%)"/>
                    </config>
                </config>
            </config>
        </config>
        <config key="column_properties"/>
        <config key="meta_data"/>
    </config>
    <config key="column_spec_21">
        <entry key="column_name" type="xstring" value="Skewness"/>
        <config key="element_names">
            <entry key="array-size" type="xint" value="0"/>
        </config>
        <config key="column_type">
            <entry key="cell_class" type="xstring" value="org.knime.core.data.def.DoubleCell"/>
        </config>
        <config key="column_domain">
            <config key="lower_bound">
                <entry key="datacell" type="xstring" value="org.knime.core.data.def.DoubleCell"/>
                <config key="org.knime.core.data.def.DoubleCell">
                    <entry key="DoubleCell" type="xdouble" value="0.0"/>
                </config>
            </config>
            <config key="upper_bound">
                <entry key="datacell" type="xstring" value="org.knime.core.data.def.DoubleCell"/>
                <config key="org.knime.core.data.def.DoubleCell">
                    <entry key="DoubleCell" type="xdouble" value="4.828821149344662"/>
                </config>
            </config>
        </config>
        <config key="column_properties"/>
        <config key="meta_data"/>
    </config>
    <config key="column_spec_22">
        <entry key="column_name" type="xstring" value="Kurtosis"/>
        <config key="element_names">
            <entry key="array-size" type="xint" value="0"/>
        </config>
        <config key="column_type">
            <entry key="cell_class" type="xstring" value="org.knime.core.data.def.DoubleCell"/>
        </config>
        <config key="column_domain">
            <config key="lower_bound">
                <entry key="datacell" type="xstring" value="org.knime.core.data.def.DoubleCell"/>
                <config key="org.knime.core.data.def.DoubleCell">
                    <entry key="DoubleCell" type="xdouble" value="-1.1999999999999995"/>
                </config>
            </config>
            <config key="upper_bound">
                <entry key="datacell" type="xstring" value="org.knime.core.data.def.DoubleCell"/>
                <config key="org.knime.core.data.def.DoubleCell">
                    <entry key="DoubleCell" type="xdouble" value="43.67840125595212"/>
                </config>
            </config>
        </config>
        <config key="column_properties"/>
        <config key="meta_data"/>
    </config>
</config>
